eventual/__init__.py
eventual/abc/__init__.py
eventual/abc/broker.py
eventual/abc/guarantee.py
eventual/abc/registry.py
eventual/abc/repository.py
eventual/abc/router.py
eventual/abc/schedule.py
eventual/abc/work_unit.py
eventual/lifespan.py
eventual/model/__init__.py
eventual/model/entity.py
eventual/model/event.py
eventual/py.typed
eventual/registry.py
eventual/router.py
eventual/scheduler.py
eventual/util/__init__.py
eventual/util/tz.py
eventual-0.7.0.dist-info/WHEEL
eventual-0.7.0.dist-info/METADATA
eventual-0.7.0.dist-info/RECORD
