Metadata-Version: 2.1
Name: eventual
Version: 0.7.0
Summary: 
Author: Ivan Dmitriesvkii
Author-email: ivan.dmitrievsky@gmail.com
Requires-Python: >=3.7,<4.0
Classifier: Programming Language :: Python :: 3
Classifier: Programming Language :: Python :: 3.7
Classifier: Programming Language :: Python :: 3.8
Classifier: Programming Language :: Python :: 3.9
Provides-Extra: rmq
Provides-Extra: tortoise
Requires-Dist: anyio (>=3.0.1,<4.0.0)
Requires-Dist: eventual-rmq (>=0,<1); extra == "rmq"
Requires-Dist: eventual-tortoise (>=0,<1); extra == "tortoise"
Requires-Dist: pytz (>=2021.1,<2022.0)
Requires-Dist: typing-extensions (>=3.10.0,<4.0.0); python_version < "3.8"
